setbot.py
setbot-0.1.1a1.dist-info/entry_points.txt
setbot-0.1.1a1.dist-info/WHEEL
setbot-0.1.1a1.dist-info/METADATA
setbot-0.1.1a1.dist-info/RECORD
